{
    "snacks": [
        {
            "id": "1",
            "name": "Gulab Jamun 1kg",
            "price": "149.00",
            "offer": 35,
            "description": "The beautiful range of Apple Naturalé that has an exciting mix of natural ingredients. With the Goodness of 100% Natural Ingredients",
            "image": "https://www.jiomart.com/images/product/600x600/491135485/crave-gulab-jamun-1-kg-product-images-o491135485-p491135485-0-202203170955.jpg",
            "category": "snacks",
            "veg": true
        },
        {
            "id": "2",
            "name": "Britania Bourbon 150g",
            "price": "26.00",
            "offer": 17,
            "description": "The beautiful range of Apple Naturalé that has an exciting mix of natural ingredients. With the Goodness of 100% Natural Ingredients",
            "image": "https://www.jiomart.com/images/product/600x600/490005349/britannia-bourbon-the-original-cream-biscuits-150-g-product-images-o490005349-p490005349-0-202203150315.jpg",
            "category": "snacks",
            "veg": true
        },
        {
            "id": "3",
            "name": "Prigles Sour Cream",
            "price": "89.00",
            "offer": 31,
            "description": "The beautiful range of Apple Naturalé that has an exciting mix of natural ingredients. With the Goodness of 100% Natural Ingredients",
            "image": "https://www.jiomart.com/images/product/600x600/491129205/pringles-sour-cream-and-onion-potato-chips-107-g-product-images-o491129205-p590032696-0-202203170557.jpg",
            "category": "snacks",
            "veg": true
        },
        {
            "id": "4",
            "name": "Haldiram's Murukku",
            "price": "60.00",
            "offer": 45,
            "description": "The beautiful range of Apple Naturalé that has an exciting mix of natural ingredients. With the Goodness of 100% Natural Ingredients",
            "image": "https://www.jiomart.com/images/product/600x600/490617276/haldiram-s-nagpur-murukku-200-g-product-images-o490617276-p490617276-0-202203150628.jpg",
            "category": "snacks",
            "veg": true
        },
        {
            "id": "5",
            "name": "Soanpapdi 400g",
            "price": "179.00",
            "offer": 26,
            "description": "The beautiful range of Apple Naturalé that has an exciting mix of natural ingredients. With the Goodness of 100% Natural Ingredients",
            "image": "https://www.jiomart.com/images/product/600x600/491085878/crave-premium-soanpapdi-400-g-product-images-o491085878-p491085878-0-202203170908.jpg",
            "category": "snacks",
            "veg": true
        },
        {
            "id": "6",
            "name": "Banana Yellaki 12 pcs (Approx 750 g)",
            "price": "109.00",
            "offer": 4,
            "description": "The beautiful range of Apple Naturalé that has an exciting mix of natural ingredients. With the Goodness of 100% Natural Ingredients",
            "image": "https://www.jiomart.com/images/product/600x600/590001655/banana-yellaki-12-pcs-approx-750-g-1000-g-product-images-o590001655-p590041069-0-202203152123.jpg",
            "category": "snacks",
            "veg": true
        },
        {
            "id": "7",
            "name": "Dates Imported (Approx 400 g - 500 g)",
            "price": "179.00",
            "offer": 27,
            "description": "The beautiful range of Apple Naturalé that has an exciting mix of natural ingredients. With the Goodness of 100% Natural Ingredients",
            "image": "https://www.jiomart.com/images/product/600x600/590002744/dates-imported-approx-400-g-500-g-product-images-o590002744-p590002744-0-202203170240.jpg",
            "category": "snacks",
            "veg": true
        },
        {
            "id": "8",
            "name": "Pomegranate Economy 6 pcs (Pack)",
            "price": "249.00",
            "offer": 57,
            "description": "The beautiful range of Apple Naturalé that has an exciting mix of natural ingredients. With the Goodness of 100% Natural Ingredients",
            "image": "https://www.jiomart.com/images/product/600x600/590001268/pomegranate-economy-6-pcs-pack-product-images-o590001268-p590485022-0-202203150746.jpg",
            "category": "snacks",
            "veg": true
        },
        {
            "id": "9",
            "name": "Plum Imported 4 pcs",
            "price": "69.00",
            "offer": 11,
            "description": "The beautiful range of Apple Naturalé that has an exciting mix of natural ingredients. With the Goodness of 100% Natural Ingredients",
            "image": "https://www.jiomart.com/images/product/600x600/590001570/plum-imported-4-pcs-product-images-o590001570-p593727906-0-202209121634.jpg",
            "category": "snacks",
            "veg": true
        },
        {
            "id": "10",
            "name": " Sapota 6 pcs (Pack)",
            "price": "99.00",
            "offer": 19,
            "description": "The beautiful range of Apple Naturalé that has an exciting mix of natural ingredients. With the Goodness of 100% Natural Ingredients",
            "image": "https://www.jiomart.com/images/product/600x600/590003068/sapota-6-pcs-pack-approx-450-g-550-g-product-images-o590003068-p590309513-0-202208101342.jpg",
            "category": "snacks",
            "veg": true
        }
    ]
}
